khlbot/__init__.py
khlbot/common.py
khlbot/config.py
khlbot/core/BaseHandler.py
khlbot/core/Bot.py
khlbot/core/Commander.py
khlbot/core/Handler.py
khlbot/core/KHLWss.py
khlbot/core/Logger.py
khlbot/core/__init__.py
khlbot/khl/APIMetaclass.py
khlbot/khl/ChannelMessage.py
khlbot/khl/ChannelMessageAPI.py
khlbot/khl/Event.py
khlbot/khl/Extra.py
khlbot/khl/GuildAPI.py
khlbot/khl/User.py
khlbot/khl/__init__.py
khlbot/khl/utils.py
khlbot-0.22.dist-info/LICENSE
khlbot-0.22.dist-info/METADATA
khlbot-0.22.dist-info/WHEEL
khlbot-0.22.dist-info/top_level.txt
khlbot-0.22.dist-info/RECORD
