Metadata-Version: 2.1
Name: khlbot
Version: 0.22
Summary: Robot framework for KaiHeiLa
Home-page: https://github.com/RMTT/khlbot
Author: RMT
Author-email: d.rong@outlook.com
License: UNKNOWN
Platform: UNKNOWN
Classifier: Programming Language :: Python :: 3.8
Classifier: License :: OSI Approved :: MIT License
Classifier: Operating System :: OS Independent
Requires-Dist: requests
Requires-Dist: websockets
